[
    {
        "id": 1,
        "nombre": "Buckets",
        "precio": 1500,
        "cantidad": 1,
        "img": "img/bucket.jpg",
        "descripcion": "8 PIEZAS DE POLLO. ELEGÍ NUESTRA TRADICIONAL RECETA ORIGINAL Y/O LA CRUJIENTE RECETA CRISPY"
    },
    {
        "id": 2,
        "nombre": "Box",
        "precio": 1200,
        "cantidad": 1,
        "img": "img/box.jpg",
        "descripcion": "1 SUPER CRUNCH, 1 POPCORN SHAKER CHICO + SALSA, 2 ALITAS. INCLUYE PAPAS Y GASEOSA MEDIANAS."
    },
    {
        "id": 3,
        "nombre": "Sandwitch",
        "precio": 1000,
        "cantidad": 1,
        "img": "img/sandwitch.jpg",
        "descripcion": "SANDWICH DE POLLO CRISPY CON LECHUGA, TOMATE, BACON, SALSA BBQ, QUESO Y PAN BRIOCHE."
    },
    {
        "id": 4,
        "nombre": "Postres",
        "precio": 800,
        "cantidad": 1,
        "img": "img/postres.jpg",
        "descripcion": "TURRÓN CON MANÍ O CHOCOLATES, COMBINADA CON TU SALSA FAVORITA DE DULCE DE LECHE, CHOCOLATE O FRUTILLA."
    },
    {
        "id": 5,
        "nombre": "Snacks",
        "precio": 900,
        "cantidad": 1,
        "img": "img/snack.jpg",
        "descripcion": "TIERNOS BOCADOS DE POLLO EMPANIZADOS CON NUESTRA CRUJIENTE RECETA CRISPY. PEDILA AHORA EN TAMAÑO NORMAL Y GRANDE"
    },
    {
        "id": 6,
        "nombre": "Alitas",
        "precio": 700,
        "cantidad": 1,
        "img": "img/alitas.jpg",
        "descripcion": "CRUJIENTES ALITAS EMPANIZADAS CON NUESTRA RECETA CRISPY. PEDILA AHORA EN TAMAÑO NORMAL Y GRANDE"
    },
    {
        "id": 7,
        "nombre": "Papas",
        "precio": 500,
        "cantidad": 1,
        "img": "img/papas-fritas.jpeg",
        "descripcion": "NUESTRAS TRADICIONALES PAPAS FRITAS. PEDILA AHORA EN TAMAÑO PEQUEÑO, NORMAL Y GRANDE"
    },
    {
        "id": 8,
        "nombre": "Puré",
        "precio": 850,
        "cantidad": 1,
        "img": "img/pure con gravy.jpg",
        "descripcion": "PURÉ DE PAPAS CON DELICIOSA SALSA GRAVY. PEDILA AHORA EN TAMAÑO PEQUEÑO, NORMAL Y GRANDE"
    }
]